{
  "date": "2026-01-08T14:04:51.921Z",
  "build": 790,
  "version": "2.101.97",
  "metrics": {
    "fileSizeMB": 4.88,
    "lineCount": 102442,
    "testCount": 0,
    "testStatus": "unknown",
    "commandCount": 218,
    "tbCommandCount": 96,
    "viewCount": 9,
    "views": [
      "readonly",
      "embed",
      "gantt",
      "calendar",
      "treemap",
      "mindmap",
      "canvas",
      "3d",
      "tree"
    ],
    "patternCount": 20,
    "keyboardHandlers": 47,
    "windowExposedCount": 391
  },
  "features": {
    "Gallery (SubmissionInbox)": true,
    "Atlas (TreeRegistry)": true,
    "Focus Mode": true,
    "Mind Map": true,
    "TTS (speakNode)": true,
    "Chrome Extension": true,
    "MCP Bridge": true,
    "Hyperedges": true,
    "Gantt View": true,
    "Calendar View": true,
    "3D View": true,
    "Canvas View": true,
    "Live Sync (Firebase)": true,
    "Image Analysis": true,
    "TB Structured Tool Use": true
  }
}